Metadata-Version: 1.0
Name: NaiveDE
Version: 1.2.0
Summary: The most trivial DE test based on likelihood ratio tests
Home-page: UNKNOWN
Author: Valentine Svensson
Author-email: valentine@nxn.se
License: MIT
Platform: UNKNOWN
